gkec/__init__.py
gkec/gkec.py
gkec-0.1.1.dist-info/LICENSE
gkec-0.1.1.dist-info/METADATA
gkec-0.1.1.dist-info/WHEEL
gkec-0.1.1.dist-info/top_level.txt
gkec-0.1.1.dist-info/RECORD
